asdf/__init__.py
asdf/_asdf.py
asdf/_compression.py
asdf/_convenience.py
asdf/_display.py
asdf/_dump.py
asdf/_entry_points.py
asdf/_helpers.py
asdf/_io.py
asdf/_node_info.py
asdf/_version.py
asdf/config.py
asdf/conftest.py
asdf/constants.py
asdf/exceptions.py
asdf/generic_io.py
asdf/lazy_nodes.py
asdf/reference.py
asdf/resource.py
asdf/schema.py
asdf/search.py
asdf/tagged.py
asdf/treeutil.py
asdf/util.py
asdf/versioning.py
asdf/yamlutil.py
asdf/_block/__init__.py
asdf/_block/callback.py
asdf/_block/exceptions.py
asdf/_block/external.py
asdf/_block/io.py
asdf/_block/key.py
asdf/_block/manager.py
asdf/_block/options.py
asdf/_block/reader.py
asdf/_block/store.py
asdf/_block/writer.py
asdf/_commands/__init__.py
asdf/_commands/defragment.py
asdf/_commands/diff.py
asdf/_commands/edit.py
asdf/_commands/exploded.py
asdf/_commands/extension.py
asdf/_commands/info.py
asdf/_commands/main.py
asdf/_commands/search.py
asdf/_commands/tags.py
asdf/_commands/to_yaml.py
asdf/_commands/validate.py
asdf/_core/__init__.py
asdf/_core/_extensions.py
asdf/_core/_integration.py
asdf/_core/_converters/__init__.py
asdf/_core/_converters/complex.py
asdf/_core/_converters/constant.py
asdf/_core/_converters/external_reference.py
asdf/_core/_converters/integer.py
asdf/_core/_converters/ndarray.py
asdf/_core/_converters/reference.py
asdf/_core/_converters/tree.py
asdf/_core/_validators/__init__.py
asdf/_core/_validators/ndarray.py
asdf/_extern/__init__.py
asdf/_extern/atomicfile.py
asdf/_jsonschema/COPYING
asdf/_jsonschema/README.md
asdf/_jsonschema/__init__.py
asdf/_jsonschema/_format.py
asdf/_jsonschema/_legacy_validators.py
asdf/_jsonschema/_types.py
asdf/_jsonschema/_utils.py
asdf/_jsonschema/_validators.py
asdf/_jsonschema/conftest.py
asdf/_jsonschema/exceptions.py
asdf/_jsonschema/protocols.py
asdf/_jsonschema/validators.py
asdf/_jsonschema/json/.gitignore
asdf/_jsonschema/json/CONTRIBUTING.md
asdf/_jsonschema/json/LICENSE
asdf/_jsonschema/json/README.md
asdf/_jsonschema/json/package.json
asdf-5.1.0.dist-info/licenses/LICENSE
asdf-5.1.0.dist-info/METADATA
asdf-5.1.0.dist-info/WHEEL
asdf-5.1.0.dist-info/entry_points.txt
asdf-5.1.0.dist-info/top_level.txt
asdf-5.1.0.dist-info/RECORD
